resultsFile/__init__.py
resultsFile/getFile.py
resultsFile/Modules/__init__.py
resultsFile/Modules/gamessFile.py
resultsFile/Modules/gaussianFile.py
resultsFile/Modules/molproFile.py
resultsFile/Modules/wfnFile.py
resultsFile/Modules/xmvbFile.py
resultsFile/lib/__init__.py
resultsFile/lib/atom.py
resultsFile/lib/basis.py
resultsFile/lib/csf.py
resultsFile/lib/fortranBinary.py
resultsFile/lib/integral.py
resultsFile/lib/library.py
resultsFile/lib/orbital.py
resultsFile-2.4.dist-info/LICENSE
resultsFile-2.4.dist-info/METADATA
resultsFile-2.4.dist-info/WHEEL
resultsFile-2.4.dist-info/top_level.txt
resultsFile-2.4.dist-info/RECORD
