Metadata-Version: 2.1
Name: resultsFile
Version: 2.4
Summary: Module for reading output files of quantum chemistry codes.
Home-page: https://gitlab.com/scemama/resultsFile
Download-URL: https://gitlab.com/scemama/resultsFile/-/archive/v2.3/resultsFile-v2.3.tar.gz
Author: Anthony Scemama
Author-email: scemama@irsamc.ups-tlse.fr
License: UNKNOWN
Keywords: quantum chemistry,GAMESS,Gaussian
Platform: UNKNOWN
Classifier: Programming Language :: Python :: 3
Classifier: License :: OSI Approved :: GNU General Public License v2 or later (GPLv2+)
Classifier: Operating System :: POSIX :: Linux
License-File: LICENSE
